[
  {
    "status": "max_steps_exceeded",
    "history": [
      {
        "tool": "jokes_search_for_chuck_norris"
      },
      {
        "tool": "get_math_fact_for_numbers",
        "output": "{'text': 'the smallest natural number representable in two different ways as a sum of two positive cubes, as Ramanujan stated on the spot', 'number': 1729, 'found': True, 'type': 'math'}"
      }
    ],
    "trace": [
      {
        "type": "action",
        "tool": "jokes_random_for_chuck_norris",
        "arguments": {},
        "status": "rejected",
        "reason": {
          "type": "temporal_violation",
          "required_before": "jokes_search_for_chuck_norris",
          "missing": "jokes_search_for_chuck_norris",
          "current": "jokes_random_for_chuck_norris"
        }
      },
      {
        "type": "action",
        "tool": "jokes_search_for_chuck_norris",
        "arguments": {
          "query": "Chuck Norris"
        },
        "status": "accepted",
        "reason": null
      },
      {
        "type": "action",
        "tool": "get_math_fact_for_numbers",
        "arguments": {
          "number": "1729"
        },
        "status": "accepted",
        "reason": null
      }
    ]
  },
  {
    "status": "premature_finish",
    "history": [
      {
        "tool": "Finish"
      }
    ],
    "trace": [
      {
        "type": "action",
        "tool": "Finish",
        "arguments": {
          "return_type": "give_answer",
          "final_answer": "For validating card numbers, I recommend using the 'validate_card_number_for_luhn_algorithm' API. To check its service status, use the 'service_status_for_luhn_algorithm' API."
        },
        "status": "accepted",
        "reason": null
      }
    ]
  },
  {
    "status": "finished",
    "history": [
      {
        "tool": "get_word_for_random_word_api",
        "output": "{'word': 'counterpreparation'}"
      },
      {
        "tool": "country_details_for_referential_db"
      },
      {
        "tool": "Finish"
      }
    ],
    "trace": [
      {
        "type": "action",
        "tool": "get_word_for_random_word_api",
        "arguments": {},
        "status": "accepted",
        "reason": null
      },
      {
        "type": "action",
        "tool": "country_details_for_referential_db",
        "arguments": {
          "countrycode": "US"
        },
        "status": "accepted",
        "reason": null
      },
      {
        "type": "action",
        "tool": "Finish",
        "arguments": {
          "return_type": "give_answer",
          "final_answer": "Here is a random word to spark your creativity: counterpreparation. Information about the country with the country code 'US': United States of America (USA) is a federal republic consisting of 50 states, a federal district, five major self-governing territories, and various possessions."
        },
        "status": "accepted",
        "reason": null
      }
    ]
  },
  {
    "status": "max_steps_exceeded",
    "history": [
      {
        "tool": "roll_for_diceforge",
        "output": "{'dice': [{'sides': 6, 'results': [3], 'modifier': 5, 'total': 8}], 'total': 8}"
      },
      {
        "tool": "roll_for_diceforge",
        "output": "{'dice': [{'sides': 6, 'results': [3], 'modifier': 5, 'total': 8}], 'total': 8}"
      },
      {
        "tool": "roll_for_diceforge",
        "output": "{'dice': [{'sides': 6, 'results': [3], 'modifier': 5, 'total': 8}], 'total': 8}"
      }
    ],
    "trace": [
      {
        "type": "action",
        "tool": "roll_for_diceforge",
        "arguments": {
          "sides": [
            20,
            10,
            6
          ],
          "count": [
            1,
            1,
            1
          ]
        },
        "status": "accepted",
        "reason": null
      },
      {
        "type": "action",
        "tool": "roll_for_diceforge",
        "arguments": {
          "sides": [
            20,
            10,
            6
          ],
          "count": [
            1,
            1,
            1
          ]
        },
        "status": "accepted",
        "reason": null
      },
      {
        "type": "action",
        "tool": "roll_for_diceforge",
        "arguments": {
          "sides": [
            20,
            10,
            6
          ],
          "count": [
            1,
            1,
            1
          ]
        },
        "status": "accepted",
        "reason": null
      }
    ]
  },
  {
    "status": "finished",
    "history": [
      {
        "tool": "stock_splits_for_freedom_finance",
        "output": "{'total': 1, 'offset': 0, 'results': [{'date': '2022-06-06', 'before': 20, 'after': 1}], 'responseStatus': None}"
      },
      {
        "tool": "dividends_for_freedom_finance",
        "output": "{'total': 0, 'offset': 0, 'results': [], 'responseStatus': None}"
      },
      {
        "tool": "Finish"
      }
    ],
    "trace": [
      {
        "type": "action",
        "tool": "stock_splits_for_freedom_finance",
        "arguments": {
          "symbol": "AMZN"
        },
        "status": "accepted",
        "reason": null
      },
      {
        "type": "action",
        "tool": "dividends_for_freedom_finance",
        "arguments": {
          "symbol": "AMZN"
        },
        "status": "accepted",
        "reason": null
      },
      {
        "type": "action",
        "tool": "Finish",
        "arguments": {
          "return_type": "give_answer",
          "final_answer": "For the AMZN symbol, there was one stock split on June 6, 2022, where the stock split ratio was 1:20. No dividend history was found for this symbol."
        },
        "status": "accepted",
        "reason": null
      }
    ]
  },
  {
    "status": "max_steps_exceeded",
    "history": [
      {
        "tool": "quote_for_quotes",
        "output": "{'quote': 'An Apple a day keeps you busy anyway', 'author': 'Sahil'}"
      },
      {
        "tool": "quote_for_quotes",
        "output": "{'quote': 'An Apple a day keeps you busy anyway', 'author': 'Sahil'}"
      },
      {
        "tool": "jokes_random_for_chuck_norris"
      }
    ],
    "trace": [
      {
        "type": "action",
        "tool": "quote_for_quotes",
        "arguments": {},
        "status": "accepted",
        "reason": null
      },
      {
        "type": "action",
        "tool": "quote_for_quotes",
        "arguments": {},
        "status": "accepted",
        "reason": null
      },
      {
        "type": "action",
        "tool": "jokes_random_for_chuck_norris",
        "arguments": {},
        "status": "accepted",
        "reason": null
      }
    ]
  },
  {
    "status": "max_steps_exceeded",
    "history": [
      {
        "tool": "series_list_api_for_fantasy_cricket"
      },
      {
        "tool": "upcoming_matches_api_for_fantasy_cricket",
        "output": "[]"
      }
    ],
    "trace": [
      {
        "type": "action",
        "tool": "series_list_api_for_fantasy_cricket",
        "arguments": {},
        "status": "accepted",
        "reason": null
      },
      {
        "type": "action",
        "tool": "upcoming_matches_api_for_fantasy_cricket",
        "arguments": {},
        "status": "accepted",
        "reason": null
      },
      {
        "type": "no_action",
        "step": 2
      }
    ]
  }
]